biosemi_enaml/__init__.py
biosemi_enaml/channel_maps.py
biosemi_enaml/electrode_coords.py
biosemi_enaml/electrode_coords_32.csv
biosemi_enaml/electrode_coords_64.csv
biosemi_enaml/electrode_selector.py
biosemi_enaml/electrode_selector_view.enaml
biosemi_enaml/exg_coords.csv
biosemi_enaml/mapped_electrode_coords_32_exg.csv
biosemi_enaml/mapped_electrode_coords_64_exg.csv
biosemi_enaml/modifier_button.py
biosemi_enaml/version.py
biosemi_enaml-0.0.1.dist-info/licenses/LICENSE.txt
biosemi_enaml-0.0.1.dist-info/METADATA
biosemi_enaml-0.0.1.dist-info/WHEEL
biosemi_enaml-0.0.1.dist-info/top_level.txt
biosemi_enaml-0.0.1.dist-info/RECORD
