Metadata-Version: 2.4
Name: biosemi-enaml
Version: 0.0.1
Summary: Widgets for working with Biosemi system
Author-email: Brad Buran <buran@ohsu.edu>
Maintainer-email: Brad Buran <buran@ohsu.edu>
License: MIT License
Requires-Python: >=3.7
License-File: LICENSE.txt
Requires-Dist: enaml>=0.13.0
Requires-Dist: psiaudio
Dynamic: license-file
